doctopus/__init__.py
doctopus-0.0.1.dist-info/METADATA
doctopus-0.0.1.dist-info/WHEEL
doctopus-0.0.1.dist-info/top_level.txt
doctopus-0.0.1.dist-info/RECORD
