Metadata-Version: 2.1
Name: doctopus
Version: 0.0.1
Summary: Doctopus doc generator
Home-page: https://github.com/cjkoral/doctopus
Author: CJ Koral
Author-email: christopher.koral@gmail.com
License: UNKNOWN
Keywords: docs,documentation,markdown,doctopus
Platform: UNKNOWN
Classifier: Programming Language :: Python :: 3
Classifier: Programming Language :: Python :: 3.6
